compas_rcf/__init__.py
compas_rcf/_version.py
compas_rcf-0.3.1.dist-info/AUTHORS.md
compas_rcf-0.3.1.dist-info/LICENSE
compas_rcf-0.3.1.dist-info/METADATA
compas_rcf-0.3.1.dist-info/WHEEL
compas_rcf-0.3.1.dist-info/top_level.txt
compas_rcf-0.3.1.dist-info/RECORD
