Metadata-Version: 2.1
Name: compas-rcf
Version: 0.3.1
Summary: python module for MAS DFAB project Rapid Clay Formations
Home-page: https://github.com/tetov/compas_rcf
Author: Anton T Johansson
Author-email: anton@tetov.se
License: MIT
Project-URL: Repository, https://github.com/compas-dev/compas
Project-URL: Issues, https://github.com/compas-dev/compas/issues
Project-URL: Documentation, https://compas_rcf.tetov.se/
Keywords: architecture,engineering,fabrication,construction
Platform: UNKNOWN
Classifier: Development Status :: 7 - Inactive
Classifier: Intended Audience :: Developers
Classifier: Topic :: Scientific/Engineering
Classifier: License :: OSI Approved :: MIT License
Classifier: Operating System :: Unix
Classifier: Operating System :: POSIX
Classifier: Operating System :: Microsoft :: Windows
Classifier: Programming Language :: Python
Classifier: Programming Language :: Python :: 3
Classifier: Programming Language :: Python :: 3.7
Classifier: Programming Language :: Python :: 3.8
Classifier: Programming Language :: Python :: Implementation :: CPython
Classifier: Programming Language :: Python :: Implementation :: IronPython
Requires-Python: >=3.7
Requires-Dist: rapid-clay-formations-fab
